castyllo/__init__.py
castyllo/castyllo.py
castyllo-0.0.1.dev1.dist-info/LICENSE
castyllo-0.0.1.dev1.dist-info/METADATA
castyllo-0.0.1.dev1.dist-info/WHEEL
castyllo-0.0.1.dev1.dist-info/top_level.txt
castyllo-0.0.1.dev1.dist-info/RECORD
