Metadata-Version: 2.1
Name: castyllo
Version: 0.0.1.dev1
Summary: A testing package for Jupyter
Home-page: https://github.com/bkief/castyllo
Author: Brian Kiefer
Author-email: bkief22@outlook.com
License: UNKNOWN
Project-URL: Bug Reports, https://github.com/bkief/castyllo/issues
Project-URL: Source, https://github.com/bkief/castyllo/
Keywords: testing jupyter ipython
Platform: UNKNOWN
Classifier: License :: OSI Approved :: Apache Software License
Classifier: Programming Language :: Python :: 3
Classifier: Programming Language :: Python :: 3.4
Classifier: Programming Language :: Python :: 3.5
Classifier: Programming Language :: Python :: 3.6
Classifier: Programming Language :: Python :: 3.7
Classifier: Operating System :: MacOS
Classifier: Operating System :: Microsoft
Classifier: Operating System :: POSIX
Classifier: Operating System :: OS Independent
Classifier: Framework :: Jupyter
Requires-Python: >=3, <4
Requires-Dist: jupyter
Requires-Dist: papermill
